block/__init__.py
block/__version__.py
block/compare_tdiuc_test.py
block/compare_tdiuc_val.py
block/compare_vqa2_val.py
block/compare_vrd_test.py
block/compare_vrd_val.py
block/datasets/__init__.py
block/datasets/factory.py
block/datasets/tdiuc.py
block/datasets/vg.py
block/datasets/vqa2.py
block/datasets/vqa2vg.py
block/datasets/vqa_utils.py
block/datasets/vrd.py
block/models/__init__.py
block/models/criterions/__init__.py
block/models/criterions/factory.py
block/models/criterions/kl_divergence.py
block/models/criterions/vqa_cross_entropy.py
block/models/criterions/vrd_bce.py
block/models/metrics/__init__.py
block/models/metrics/compute_oe_accuracy.py
block/models/metrics/factory.py
block/models/metrics/vqa_accuracies.py
block/models/metrics/vqa_accuracy.py
block/models/metrics/vrd_predicate.py
block/models/metrics/vrd_rel_phrase.py
block/models/metrics/vrd_utils.py
block/models/networks/__init__.py
block/models/networks/factory.py
block/models/networks/mlp.py
block/models/networks/vqa_net.py
block/models/networks/vrd_net.py
block/models/networks/fusions/__init__.py
block/models/networks/fusions/compactbilinearpooling.py
block/models/networks/fusions/factory.py
block/models/networks/fusions/fusions.py
block/optimizers/__init__.py
block/optimizers/factory.py
block/optimizers/lr_scheduler.py
block.bootstrap.pytorch-0.1.5.dist-info/LICENSE.txt
block.bootstrap.pytorch-0.1.5.dist-info/METADATA
block.bootstrap.pytorch-0.1.5.dist-info/WHEEL
block.bootstrap.pytorch-0.1.5.dist-info/top_level.txt
block.bootstrap.pytorch-0.1.5.dist-info/RECORD
