Metadata-Version: 2.1
Name: block.bootstrap.pytorch
Version: 0.1.5
Summary: BLOCK: Bilinear Superdiagonal Fusion for Visual Question Answering and Visual Relationship Detection
Home-page: https://github.com/cadene/block.bootstrap.pytorch
Author: Remi Cadene
Author-email: remi.cadene@icloud.com
License: UNKNOWN
Keywords: pytorch block vqa vrd visual question answering visual relationship detection relation bootstrap deep learning aaai
Platform: UNKNOWN
Classifier: Development Status :: 3 - Alpha
Classifier: Intended Audience :: Developers
Classifier: Topic :: Software Development :: Build Tools
Classifier: License :: OSI Approved :: MIT License
Classifier: Programming Language :: Python :: 3.7
Requires-Dist: bootstrap.pytorch
Requires-Dist: skipthoughts
Requires-Dist: pretrainedmodels
Requires-Dist: opencv-python
Requires-Dist: tqdm
Provides-Extra: mcb
Requires-Dist: cffi ; extra == 'mcb'
Requires-Dist: pytorch-fft ; extra == 'mcb'
Provides-Extra: test
Requires-Dist: pytest ; extra == 'test'
